ptimedelta/__init__.py
ptimedelta/const.py
ptimedelta/regex.py
ptimedelta/six.py
ptimedelta/to.py
ptimedelta-0.1.5.dist-info/LICENSE
ptimedelta-0.1.5.dist-info/WHEEL
ptimedelta-0.1.5.dist-info/METADATA
ptimedelta-0.1.5.dist-info/RECORD
