Metadata-Version: 2.1
Name: ptimedelta
Version: 0.1.5
Summary: Pretty Timedelta. Convert your timedelta objects to pretty strings and vice versa.
Home-page: https://github.com/antongoy/ptimedelta
License: MIT
Author: Anton Goy
Author-email: antongoy@internet.ru
Classifier: Development Status :: 3 - Alpha
Classifier: License :: OSI Approved :: MIT License
Classifier: Operating System :: OS Independent
Classifier: Programming Language :: Python
Classifier: Programming Language :: Python :: 2
Classifier: Programming Language :: Python :: 2.7
Classifier: Programming Language :: Python :: 3
Classifier: Programming Language :: Python :: 3.4
Classifier: Programming Language :: Python :: 3.5
Classifier: Programming Language :: Python :: 3.6
Classifier: Programming Language :: Python :: 3.7
Classifier: Programming Language :: Python :: 3.8
Classifier: Programming Language :: Python :: 3.9
Classifier: Topic :: Utilities
Project-URL: Repository, https://github.com/antongoy/ptimedelta
